[
    {
        "path": "404.html",
        "type": "file",
        "md5": "a66833ea4cad6e17815a965590799e76"
    },
    {
        "path": "assets",
        "type": "directory",
        "md5": false
    },
    {
        "path": "assets/css",
        "type": "directory",
        "md5": false
    },
    {
        "path": "/assets/css/editor.css",
        "type": "file",
        "md5": "e5909a88ba1158a79ba2dbf82d6b2d86"
    },
    {
        "path": "/assets/css/main.css",
        "type": "file",
        "md5": "4e960cc8ecf8b3ee62bdc1ac5aef4d8c"
    },
    {
        "path": "/assets/css/photoswipe.css",
        "type": "file",
        "md5": "da6e9be0fa855edd3610e97c1d4e38d9"
    },
    {
        "path": "/assets/css/style.css",
        "type": "file",
        "md5": "48d2f0bb7447b316e047cad2679f0726"
    },
    {
        "path": "assets/dynamic",
        "type": "directory",
        "md5": false
    },
    {
        "path": "assets/js",
        "type": "directory",
        "md5": false
    },
    {
        "path": "/assets/js/embla-carousel.umd.js",
        "type": "file",
        "md5": "f893797e9ada2ab14b385ca0f05b4d4e"
    },
    {
        "path": "/assets/js/photoswipe-ui-default.min.js",
        "type": "file",
        "md5": "d067f0883540b1ddda0e2c9ad1b14260"
    },
    {
        "path": "/assets/js/photoswipe.min.js",
        "type": "file",
        "md5": "017385b552f7e0d979e2e2fe6f324015"
    },
    {
        "path": "/assets/js/scripts.js",
        "type": "file",
        "md5": "8f7085af07de789d8224f6e789761bfa"
    },
    {
        "path": "/assets/js/scripts.min.js",
        "type": "file",
        "md5": "478747ac4d83bd1c26f103566bc76600"
    },
    {
        "path": "/assets/js/svg-fix.js",
        "type": "file",
        "md5": "7c0d2bb7276904b382e80bf2d85e8a96"
    },
    {
        "path": "/assets/js/svg-map.js",
        "type": "file",
        "md5": "ca6c56a328a905b5d9806a2667eb56a2"
    },
    {
        "path": "assets/svg",
        "type": "directory",
        "md5": false
    },
    {
        "path": "/assets/svg/gallery-icons-dark.svg",
        "type": "file",
        "md5": "0c70735af58190b563b2940b7a07007a"
    },
    {
        "path": "/assets/svg/gallery-icons-light.svg",
        "type": "file",
        "md5": "0bb1f41e2e459d23628833c37d8532f0"
    },
    {
        "path": "/assets/svg/submit-arrow.svg",
        "type": "file",
        "md5": "3731e52ff9ef24e6a85fa2434ccb6416"
    },
    {
        "path": "/assets/svg/svg-map.svg",
        "type": "file",
        "md5": "74bf56714c4baec3889d753788c9c744"
    },
    {
        "path": "authors",
        "type": "directory",
        "md5": false
    },
    {
        "path": "authors/filip-strzinek",
        "type": "directory",
        "md5": false
    },
    {
        "path": "/authors/filip-strzinek/index.html",
        "type": "file",
        "md5": "a3e5f6bc57eced0a52b4f44ddef97dfb"
    },
    {
        "path": "faq",
        "type": "directory",
        "md5": false
    },
    {
        "path": "/faq/index.html",
        "type": "file",
        "md5": "b1d88dbea8173fbf6ca72096fb26e8f6"
    },
    {
        "path": "feed.json",
        "type": "file",
        "md5": "8047f1a04ae6d597f0cff6024a3b0647"
    },
    {
        "path": "feed.xml",
        "type": "file",
        "md5": "e0a114e49689a8a1c3b79aadaf6a9c18"
    },
    {
        "path": "index.html",
        "type": "file",
        "md5": "b2089748f8d203db8d74c88ce99854fb"
    },
    {
        "path": "kde-hrajeme",
        "type": "directory",
        "md5": false
    },
    {
        "path": "/kde-hrajeme/index.html",
        "type": "file",
        "md5": "e582b9a2c009d27a18506392961263f1"
    },
    {
        "path": "mame-zajem-a-co-dal",
        "type": "directory",
        "md5": false
    },
    {
        "path": "/mame-zajem-a-co-dal/index.html",
        "type": "file",
        "md5": "970706a1b25870dcdb668265eb8f99c2"
    },
    {
        "path": "media",
        "type": "directory",
        "md5": false
    },
    {
        "path": "media/posts",
        "type": "directory",
        "md5": false
    },
    {
        "path": "media/posts/1",
        "type": "directory",
        "md5": false
    },
    {
        "path": "media/posts/1/responsive",
        "type": "directory",
        "md5": false
    },
    {
        "path": "/media/posts/1/responsive/_DSC5306-md.webp",
        "type": "file",
        "md5": "7150adb9d3a3fef26baf35e7b6939e13"
    },
    {
        "path": "/media/posts/1/responsive/_DSC5306-sm.webp",
        "type": "file",
        "md5": "d85c76c83e992d88e2537635e859fd7e"
    },
    {
        "path": "/media/posts/1/responsive/_DSC5306-xl.webp",
        "type": "file",
        "md5": "a689a63b60f29abbf234e74c177f8ec6"
    },
    {
        "path": "/media/posts/1/responsive/_DSC5306-xs.webp",
        "type": "file",
        "md5": "0064e2d9e1fab25fe2a13ed7b661485f"
    },
    {
        "path": "/media/posts/1/responsive/_DSC5306-xxl.webp",
        "type": "file",
        "md5": "4915513c310dc9dbc984d36472d52148"
    },
    {
        "path": "/media/posts/1/_DSC5306.jpg",
        "type": "file",
        "md5": "a8a8d44ed4ba2c16c86d743e6c75895f"
    },
    {
        "path": "media/posts/13",
        "type": "directory",
        "md5": false
    },
    {
        "path": "media/posts/13/gallery",
        "type": "directory",
        "md5": false
    },
    {
        "path": "/media/posts/13/gallery/adamcovi-00496-2-thumbnail.webp",
        "type": "file",
        "md5": "4c1b23159cfdc2f3a757d8a47f1cb5ed"
    },
    {
        "path": "/media/posts/13/gallery/adamcovi-00496-2.jpg",
        "type": "file",
        "md5": "7110eae2f6a98cb901c28e53503af34c"
    },
    {
        "path": "/media/posts/13/gallery/dobrocinna-akce_2024-2-thumbnail.webp",
        "type": "file",
        "md5": "1b4861b0a5365598012f0ef5daae317b"
    },
    {
        "path": "/media/posts/13/gallery/dobrocinna-akce_2024-2.jpg",
        "type": "file",
        "md5": "12f25468f47419f336e51d7174e7627a"
    },
    {
        "path": "/media/posts/13/gallery/janickovi_2019-2-thumbnail.webp",
        "type": "file",
        "md5": "54b7c592652e3a7f2082d901969c4ffe"
    },
    {
        "path": "/media/posts/13/gallery/janickovi_2019-2.jpg",
        "type": "file",
        "md5": "97e3088d99c715b5d555a2089d8db05e"
    },
    {
        "path": "/media/posts/13/gallery/janickovi_2020-2-thumbnail.webp",
        "type": "file",
        "md5": "5b124b1913e6e1d81951b8fc99f79a98"
    },
    {
        "path": "/media/posts/13/gallery/janickovi_2020-2.jpeg",
        "type": "file",
        "md5": "74ae3f31e671a5e8f7d24e5dbc078855"
    },
    {
        "path": "/media/posts/13/gallery/matuskovi_2021-2-thumbnail.webp",
        "type": "file",
        "md5": "6810267b2187f814ab7ded065eca09aa"
    },
    {
        "path": "/media/posts/13/gallery/matuskovi_2021-2.jpeg",
        "type": "file",
        "md5": "e752bdc8c18fd72475ac6ecfbe5f6f52"
    },
    {
        "path": "/media/posts/13/gallery/Vaskovych_sirka-thumbnail.webp",
        "type": "file",
        "md5": "3ad4d531c7c13c70be36b44595c77c6a"
    },
    {
        "path": "/media/posts/13/gallery/Vaskovych_sirka.jpg",
        "type": "file",
        "md5": "0de100457e3df4eadcb27911841978f9"
    },
    {
        "path": "/media/posts/13/gallery/_DSC5306-2-thumbnail.webp",
        "type": "file",
        "md5": "7150adb9d3a3fef26baf35e7b6939e13"
    },
    {
        "path": "/media/posts/13/gallery/_DSC5306-2.jpg",
        "type": "file",
        "md5": "a8a8d44ed4ba2c16c86d743e6c75895f"
    },
    {
        "path": "/media/posts/13/gallery/_DSC5306-thumbnail.webp",
        "type": "file",
        "md5": "7150adb9d3a3fef26baf35e7b6939e13"
    },
    {
        "path": "/media/posts/13/gallery/_DSC5306.jpg",
        "type": "file",
        "md5": "a8a8d44ed4ba2c16c86d743e6c75895f"
    },
    {
        "path": "media/posts/13/responsive",
        "type": "directory",
        "md5": false
    },
    {
        "path": "/media/posts/13/responsive/_DSC5306-md.webp",
        "type": "file",
        "md5": "7150adb9d3a3fef26baf35e7b6939e13"
    },
    {
        "path": "/media/posts/13/responsive/_DSC5306-sm.webp",
        "type": "file",
        "md5": "d85c76c83e992d88e2537635e859fd7e"
    },
    {
        "path": "/media/posts/13/responsive/_DSC5306-xl.webp",
        "type": "file",
        "md5": "a689a63b60f29abbf234e74c177f8ec6"
    },
    {
        "path": "/media/posts/13/responsive/_DSC5306-xs.webp",
        "type": "file",
        "md5": "0064e2d9e1fab25fe2a13ed7b661485f"
    },
    {
        "path": "/media/posts/13/responsive/_DSC5306-xxl.webp",
        "type": "file",
        "md5": "4915513c310dc9dbc984d36472d52148"
    },
    {
        "path": "/media/posts/13/_DSC5306.jpg",
        "type": "file",
        "md5": "a8a8d44ed4ba2c16c86d743e6c75895f"
    },
    {
        "path": "media/posts/2",
        "type": "directory",
        "md5": false
    },
    {
        "path": "/media/posts/2/filik.jpg",
        "type": "file",
        "md5": "c89ed3a88eb75b798b3eabe7dea8022a"
    },
    {
        "path": "/media/posts/2/klara-2.jpg",
        "type": "file",
        "md5": "ba87c5fc74cd56112bf115ebda41052d"
    },
    {
        "path": "media/posts/2/responsive",
        "type": "directory",
        "md5": false
    },
    {
        "path": "/media/posts/2/responsive/filik-md.webp",
        "type": "file",
        "md5": "591b0a175f6f442fe0572534a516ce9c"
    },
    {
        "path": "/media/posts/2/responsive/filik-sm.webp",
        "type": "file",
        "md5": "d66de1dfee1a41f67c852f9cfb654186"
    },
    {
        "path": "/media/posts/2/responsive/filik-xs.webp",
        "type": "file",
        "md5": "37c918e19ffec1201243a5482c765c3b"
    },
    {
        "path": "/media/posts/2/responsive/klara-2-md.webp",
        "type": "file",
        "md5": "46dc30dcb53cc5564434812f0c9a31c2"
    },
    {
        "path": "/media/posts/2/responsive/klara-2-sm.webp",
        "type": "file",
        "md5": "c9727afce27f601b06a7936777d765df"
    },
    {
        "path": "/media/posts/2/responsive/klara-2-xs.webp",
        "type": "file",
        "md5": "9c19f2f56812a053f399607022960291"
    },
    {
        "path": "/media/posts/2/responsive/uvodni-md.webp",
        "type": "file",
        "md5": "d62d06636b54462c8e69cb0bba7ad13f"
    },
    {
        "path": "/media/posts/2/responsive/uvodni-sm.webp",
        "type": "file",
        "md5": "82802e1ccbe07a56abf5da75b03f6040"
    },
    {
        "path": "/media/posts/2/responsive/uvodni-xl.webp",
        "type": "file",
        "md5": "2530102426614d66b7bdfa258b7744df"
    },
    {
        "path": "/media/posts/2/responsive/uvodni-xs.webp",
        "type": "file",
        "md5": "c0d054306468615d3c53c80939c47ee8"
    },
    {
        "path": "/media/posts/2/responsive/uvodni-xxl.webp",
        "type": "file",
        "md5": "f1a9c9ee8024b73854d2b45c42bcf440"
    },
    {
        "path": "/media/posts/2/uvodni.jpg",
        "type": "file",
        "md5": "716cfebd40ef50a84aa44b763d827a87"
    },
    {
        "path": "media/posts/3",
        "type": "directory",
        "md5": false
    },
    {
        "path": "/media/posts/3/23-11-03-21-51-36-Tereza-Plaskova.jpg",
        "type": "file",
        "md5": "39c40747c00de03e081ce34298d88f16"
    },
    {
        "path": "media/posts/3/responsive",
        "type": "directory",
        "md5": false
    },
    {
        "path": "/media/posts/3/responsive/23-11-03-21-51-36-Tereza-Plaskova-md.webp",
        "type": "file",
        "md5": "89925e5bc1ab9117fb3883c08f9486ec"
    },
    {
        "path": "/media/posts/3/responsive/23-11-03-21-51-36-Tereza-Plaskova-sm.webp",
        "type": "file",
        "md5": "43caab409b2bf89aac90fce92877e309"
    },
    {
        "path": "/media/posts/3/responsive/23-11-03-21-51-36-Tereza-Plaskova-xl.webp",
        "type": "file",
        "md5": "a2320178ca08e7a3487d29a5edaaa6cc"
    },
    {
        "path": "/media/posts/3/responsive/23-11-03-21-51-36-Tereza-Plaskova-xs.webp",
        "type": "file",
        "md5": "5b0e1d11de08ad6085e68532ceabaff7"
    },
    {
        "path": "/media/posts/3/responsive/23-11-03-21-51-36-Tereza-Plaskova-xxl.webp",
        "type": "file",
        "md5": "44d9462a0201258455b96cd69d84a23d"
    },
    {
        "path": "media/posts/5",
        "type": "directory",
        "md5": false
    },
    {
        "path": "/media/posts/5/23-11-24-19-36-54-Tereza-Plaskova-2.jpg",
        "type": "file",
        "md5": "95868af78cc236b6ac1f13a29ffc1065"
    },
    {
        "path": "/media/posts/5/23-11-24-19-36-54-Tereza-Plaskova.jpg",
        "type": "file",
        "md5": "95868af78cc236b6ac1f13a29ffc1065"
    },
    {
        "path": "media/posts/5/responsive",
        "type": "directory",
        "md5": false
    },
    {
        "path": "/media/posts/5/responsive/23-11-24-19-36-54-Tereza-Plaskova-2-md.webp",
        "type": "file",
        "md5": "d4b709f166f6f5fb43a7eefd7bdc62db"
    },
    {
        "path": "/media/posts/5/responsive/23-11-24-19-36-54-Tereza-Plaskova-2-sm.webp",
        "type": "file",
        "md5": "adadec9131d8caf4ce8d9a7868b9a017"
    },
    {
        "path": "/media/posts/5/responsive/23-11-24-19-36-54-Tereza-Plaskova-2-xs.webp",
        "type": "file",
        "md5": "bc1ecb965eb9a2c96a132f7012a09780"
    },
    {
        "path": "/media/posts/5/responsive/23-11-24-19-36-54-Tereza-Plaskova-md.webp",
        "type": "file",
        "md5": "d4b709f166f6f5fb43a7eefd7bdc62db"
    },
    {
        "path": "/media/posts/5/responsive/23-11-24-19-36-54-Tereza-Plaskova-sm.webp",
        "type": "file",
        "md5": "adadec9131d8caf4ce8d9a7868b9a017"
    },
    {
        "path": "/media/posts/5/responsive/23-11-24-19-36-54-Tereza-Plaskova-xl.webp",
        "type": "file",
        "md5": "1c3621966ed0a842248f5cdb3becd3f8"
    },
    {
        "path": "/media/posts/5/responsive/23-11-24-19-36-54-Tereza-Plaskova-xs.webp",
        "type": "file",
        "md5": "bc1ecb965eb9a2c96a132f7012a09780"
    },
    {
        "path": "/media/posts/5/responsive/23-11-24-19-36-54-Tereza-Plaskova-xxl.webp",
        "type": "file",
        "md5": "379bb89fbf6ed189fd3d36decc1ff109"
    },
    {
        "path": "media/posts/6",
        "type": "directory",
        "md5": false
    },
    {
        "path": "/media/posts/6/15-06-24-19-59-49-Tereza-Plaskova.jpg",
        "type": "file",
        "md5": "6926742d77da30b0e58d6405c4595ca9"
    },
    {
        "path": "/media/posts/6/IMG_2699-2.jpeg",
        "type": "file",
        "md5": "b6bad68f958c5668216ff8a616732ff6"
    },
    {
        "path": "/media/posts/6/IMG_2734-2.jpeg",
        "type": "file",
        "md5": "3ea8286bfdea0e7e06971e0311b18bdb"
    },
    {
        "path": "media/posts/6/responsive",
        "type": "directory",
        "md5": false
    },
    {
        "path": "/media/posts/6/responsive/15-06-24-19-59-49-Tereza-Plaskova-md.webp",
        "type": "file",
        "md5": "838ec288588b5c6fd975e64154e84fe1"
    },
    {
        "path": "/media/posts/6/responsive/15-06-24-19-59-49-Tereza-Plaskova-sm.webp",
        "type": "file",
        "md5": "17fe9ddfabb7bc2e566ab9fc5f4eaeac"
    },
    {
        "path": "/media/posts/6/responsive/15-06-24-19-59-49-Tereza-Plaskova-xl.webp",
        "type": "file",
        "md5": "96e9dce6f41d636169c9bded6c20ad48"
    },
    {
        "path": "/media/posts/6/responsive/15-06-24-19-59-49-Tereza-Plaskova-xs.webp",
        "type": "file",
        "md5": "ee9a360c3d7d25b192b9ed6799d0a133"
    },
    {
        "path": "/media/posts/6/responsive/15-06-24-19-59-49-Tereza-Plaskova-xxl.webp",
        "type": "file",
        "md5": "95111610da3df1f50f2deb157171ae40"
    },
    {
        "path": "/media/posts/6/responsive/IMG_2699-2-md.webp",
        "type": "file",
        "md5": "3a126c133050bf30bd24790fa1361d1f"
    },
    {
        "path": "/media/posts/6/responsive/IMG_2699-2-sm.webp",
        "type": "file",
        "md5": "c8d7ca0c95001aa2f1424ee69f5d3dda"
    },
    {
        "path": "/media/posts/6/responsive/IMG_2699-2-xs.webp",
        "type": "file",
        "md5": "585625c96b8fcc2e1de9a4fad43de7c0"
    },
    {
        "path": "/media/posts/6/responsive/IMG_2734-2-md.webp",
        "type": "file",
        "md5": "e0ba0146543b82e3b7a80eca6e91a729"
    },
    {
        "path": "/media/posts/6/responsive/IMG_2734-2-sm.webp",
        "type": "file",
        "md5": "1990c5857922a7f47d0fe7c7676f707c"
    },
    {
        "path": "/media/posts/6/responsive/IMG_2734-2-xs.webp",
        "type": "file",
        "md5": "5ebc85ff01a900e63557ec27675c50e8"
    },
    {
        "path": "media/posts/7",
        "type": "directory",
        "md5": false
    },
    {
        "path": "/media/posts/7/24-03-24-17-27-49-Tereza-Plaskova.jpg",
        "type": "file",
        "md5": "ffed4360b7d5af016ca6a2c45961b52e"
    },
    {
        "path": "/media/posts/7/moonday.jpg",
        "type": "file",
        "md5": "e5f5810035973902d4af9d900cc80911"
    },
    {
        "path": "media/posts/7/responsive",
        "type": "directory",
        "md5": false
    },
    {
        "path": "/media/posts/7/responsive/24-03-24-17-27-49-Tereza-Plaskova-md.webp",
        "type": "file",
        "md5": "0ab30526daf59132a51b420d48b6c66c"
    },
    {
        "path": "/media/posts/7/responsive/24-03-24-17-27-49-Tereza-Plaskova-sm.webp",
        "type": "file",
        "md5": "bf1cd08b2c5322847b7ac83851ec5e58"
    },
    {
        "path": "/media/posts/7/responsive/24-03-24-17-27-49-Tereza-Plaskova-xl.webp",
        "type": "file",
        "md5": "b60ffb9f726bdbf1510f3a96b9ee001e"
    },
    {
        "path": "/media/posts/7/responsive/24-03-24-17-27-49-Tereza-Plaskova-xs.webp",
        "type": "file",
        "md5": "1b4861b0a5365598012f0ef5daae317b"
    },
    {
        "path": "/media/posts/7/responsive/24-03-24-17-27-49-Tereza-Plaskova-xxl.webp",
        "type": "file",
        "md5": "02ec11ba5bb6a73b92a35d5884cc61da"
    },
    {
        "path": "/media/posts/7/responsive/moonday-md.webp",
        "type": "file",
        "md5": "b158b768f012e8ece354d14f39b9778f"
    },
    {
        "path": "/media/posts/7/responsive/moonday-sm.webp",
        "type": "file",
        "md5": "e1be4a930179bdacc5d17a9ae446d797"
    },
    {
        "path": "/media/posts/7/responsive/moonday-xs.webp",
        "type": "file",
        "md5": "bde3b6bffd6d8782569bcadba13ba2e7"
    },
    {
        "path": "media/posts/8",
        "type": "directory",
        "md5": false
    },
    {
        "path": "/media/posts/8/IMG_2698.jpeg",
        "type": "file",
        "md5": "90c5265f9025e88699e78cfe3d5121c7"
    },
    {
        "path": "/media/posts/8/IMG_2701.jpeg",
        "type": "file",
        "md5": "9bcca6b0fe2e65f045294a4fa6456192"
    },
    {
        "path": "/media/posts/8/IMG_2707.jpeg",
        "type": "file",
        "md5": "8c971748660544b388baf2dd2a68642a"
    },
    {
        "path": "/media/posts/8/IMG_2708.jpeg",
        "type": "file",
        "md5": "5397559e1786811da09658b9ebf8b3df"
    },
    {
        "path": "/media/posts/8/IMG_2709.jpeg",
        "type": "file",
        "md5": "6f79a06ea90fdb94884fe95a7c0be145"
    },
    {
        "path": "/media/posts/8/IMG_2710.jpeg",
        "type": "file",
        "md5": "e5bcbd24d8ab1d383dbd0c68928954f4"
    },
    {
        "path": "/media/posts/8/IMG_2712.jpeg",
        "type": "file",
        "md5": "bb59bb01ff59c0e8199c56c92fa1b9c7"
    },
    {
        "path": "/media/posts/8/IMG_2713.jpeg",
        "type": "file",
        "md5": "fadddb37fea44a5a4288f9023ec2e18b"
    },
    {
        "path": "media/posts/8/responsive",
        "type": "directory",
        "md5": false
    },
    {
        "path": "/media/posts/8/responsive/IMG_2698-md.webp",
        "type": "file",
        "md5": "c2872a13007953728adad20497659045"
    },
    {
        "path": "/media/posts/8/responsive/IMG_2698-sm.webp",
        "type": "file",
        "md5": "4dc09bf72884831649591d510b538c82"
    },
    {
        "path": "/media/posts/8/responsive/IMG_2698-xs.webp",
        "type": "file",
        "md5": "ae87fdcf57e0763b84ebb421686bad77"
    },
    {
        "path": "/media/posts/8/responsive/IMG_2701-md.webp",
        "type": "file",
        "md5": "a7ed8d0802f9f9ed7d80c4ce8cbdb5fb"
    },
    {
        "path": "/media/posts/8/responsive/IMG_2701-sm.webp",
        "type": "file",
        "md5": "43af267d3263ef578dcef199b125eed1"
    },
    {
        "path": "/media/posts/8/responsive/IMG_2701-xs.webp",
        "type": "file",
        "md5": "b8c33fc42bad670621fca64b9c871832"
    },
    {
        "path": "/media/posts/8/responsive/IMG_2707-md.webp",
        "type": "file",
        "md5": "d99df48c9cd89c5f5b9a68880f82f191"
    },
    {
        "path": "/media/posts/8/responsive/IMG_2707-sm.webp",
        "type": "file",
        "md5": "a446e146563369c88366a8a2b41f58ca"
    },
    {
        "path": "/media/posts/8/responsive/IMG_2707-xs.webp",
        "type": "file",
        "md5": "c1ff209e356871a37a126b4c29b4fc20"
    },
    {
        "path": "/media/posts/8/responsive/IMG_2708-md.webp",
        "type": "file",
        "md5": "4439f920a24a7e2e59a2a959366b9143"
    },
    {
        "path": "/media/posts/8/responsive/IMG_2708-sm.webp",
        "type": "file",
        "md5": "f8ea90f8c1e9f3dffcc0935c2cc2104d"
    },
    {
        "path": "/media/posts/8/responsive/IMG_2708-xs.webp",
        "type": "file",
        "md5": "61ab2d338921a299655861cfd2fbc7fc"
    },
    {
        "path": "/media/posts/8/responsive/IMG_2709-md.webp",
        "type": "file",
        "md5": "6abd6a36fdada42ed2e164cfdd987514"
    },
    {
        "path": "/media/posts/8/responsive/IMG_2709-sm.webp",
        "type": "file",
        "md5": "8c112048816ff9db012361a2b6035d9b"
    },
    {
        "path": "/media/posts/8/responsive/IMG_2709-xs.webp",
        "type": "file",
        "md5": "494d7d437cef0e1330c7c29137179b60"
    },
    {
        "path": "/media/posts/8/responsive/IMG_2710-md.webp",
        "type": "file",
        "md5": "e936f233e948ccc5dfe66739ab609768"
    },
    {
        "path": "/media/posts/8/responsive/IMG_2710-sm.webp",
        "type": "file",
        "md5": "7395c65fcb80d63a39ae6d7e4b420f21"
    },
    {
        "path": "/media/posts/8/responsive/IMG_2710-xs.webp",
        "type": "file",
        "md5": "f0df34a0309d2f8de1e29ab740f9ee8c"
    },
    {
        "path": "/media/posts/8/responsive/IMG_2712-md.webp",
        "type": "file",
        "md5": "8393e290607ab2ce064c79e16644c1f4"
    },
    {
        "path": "/media/posts/8/responsive/IMG_2712-sm.webp",
        "type": "file",
        "md5": "705f9809400e1c5944d9ddb992ed01fd"
    },
    {
        "path": "/media/posts/8/responsive/IMG_2712-xs.webp",
        "type": "file",
        "md5": "1b13954a87622e5a84252f449a57e26c"
    },
    {
        "path": "/media/posts/8/responsive/IMG_2713-md.webp",
        "type": "file",
        "md5": "371ea38600ea2254539f72a3e1de9b2d"
    },
    {
        "path": "/media/posts/8/responsive/IMG_2713-sm.webp",
        "type": "file",
        "md5": "551cd5c4635b1c95304cf9a9c1f0c496"
    },
    {
        "path": "/media/posts/8/responsive/IMG_2713-xs.webp",
        "type": "file",
        "md5": "092139b0832f323e33e57192bb73f297"
    },
    {
        "path": "media/posts/9",
        "type": "directory",
        "md5": false
    },
    {
        "path": "/media/posts/9/IMG_2736.jpeg",
        "type": "file",
        "md5": "2618d167f35dad43fe4facd89af1d214"
    },
    {
        "path": "media/posts/9/responsive",
        "type": "directory",
        "md5": false
    },
    {
        "path": "/media/posts/9/responsive/IMG_2736-md.webp",
        "type": "file",
        "md5": "f1ce05e312ffa112f074b185e6dcf19c"
    },
    {
        "path": "/media/posts/9/responsive/IMG_2736-sm.webp",
        "type": "file",
        "md5": "a9cbe2ae5e12b975087b10690e2a4dec"
    },
    {
        "path": "/media/posts/9/responsive/IMG_2736-xs.webp",
        "type": "file",
        "md5": "6dbc78ed87642d163eb6797740811578"
    },
    {
        "path": "media/website",
        "type": "directory",
        "md5": false
    },
    {
        "path": "/media/website/favicon-32x32.png",
        "type": "file",
        "md5": "8423dd831ff935545d7e2799c4ccc7a6"
    },
    {
        "path": "media/website/responsive",
        "type": "directory",
        "md5": false
    },
    {
        "path": "/media/website/responsive/favicon-32x32-md.webp",
        "type": "file",
        "md5": "4e7126c9f7738ccbd4eab9edf31f7bc8"
    },
    {
        "path": "/media/website/responsive/favicon-32x32-sm.webp",
        "type": "file",
        "md5": "4e7126c9f7738ccbd4eab9edf31f7bc8"
    },
    {
        "path": "/media/website/responsive/favicon-32x32-xl.webp",
        "type": "file",
        "md5": "4e7126c9f7738ccbd4eab9edf31f7bc8"
    },
    {
        "path": "/media/website/responsive/favicon-32x32-xs.webp",
        "type": "file",
        "md5": "4e7126c9f7738ccbd4eab9edf31f7bc8"
    },
    {
        "path": "/media/website/responsive/favicon-32x32-xxl.webp",
        "type": "file",
        "md5": "4e7126c9f7738ccbd4eab9edf31f7bc8"
    },
    {
        "path": "moonday",
        "type": "directory",
        "md5": false
    },
    {
        "path": "/moonday/index.html",
        "type": "file",
        "md5": "35e538c3bf507baad91e3783314281c7"
    },
    {
        "path": "o-nas",
        "type": "directory",
        "md5": false
    },
    {
        "path": "/o-nas/index.html",
        "type": "file",
        "md5": "f23f9e651e01e93de771b9cf9ea6fde6"
    },
    {
        "path": "o-nas-2",
        "type": "directory",
        "md5": false
    },
    {
        "path": "/o-nas-2/index.html",
        "type": "file",
        "md5": "ca5a89f32149cf5a5c215ef22d4527a2"
    },
    {
        "path": "proc-si-nas-vybrat",
        "type": "directory",
        "md5": false
    },
    {
        "path": "/proc-si-nas-vybrat/index.html",
        "type": "file",
        "md5": "68f212982e0d2ed466ea67d5bb6830ac"
    },
    {
        "path": "reference",
        "type": "directory",
        "md5": false
    },
    {
        "path": "/reference/index.html",
        "type": "file",
        "md5": "4ef6e39721243b1f174598b1a390e62f"
    },
    {
        "path": "reference-2",
        "type": "directory",
        "md5": false
    },
    {
        "path": "/reference-2/index.html",
        "type": "file",
        "md5": "774e1d5b54e1f9865972f53ba777a8b7"
    },
    {
        "path": "robots.txt",
        "type": "file",
        "md5": "3d49ebb6d909d0d979415fbeba62ee0f"
    },
    {
        "path": "sitemap.xml",
        "type": "file",
        "md5": "4ef02bb0430e206bcd5df5a8340b6751"
    },
    {
        "path": "sitemap.xsl",
        "type": "file",
        "md5": "51a7bcec43fa1ef0366100d5c2edbe75"
    },
    {
        "path": "tags",
        "type": "directory",
        "md5": false
    },
    {
        "path": "/tags/index.html",
        "type": "file",
        "md5": "40b9b42bfd03914dc97446ddee5535bc"
    },
    {
        "path": "test-pages",
        "type": "directory",
        "md5": false
    },
    {
        "path": "/test-pages/index.html",
        "type": "file",
        "md5": "59e0b82aef013d35c042cd924f6385b5"
    },
    {
        "path": "ukazky",
        "type": "directory",
        "md5": false
    },
    {
        "path": "/ukazky/index.html",
        "type": "file",
        "md5": "46b709acfb8d4e3ed55922c116e8c769"
    },
    {
        "path": "ukazky-2",
        "type": "directory",
        "md5": false
    },
    {
        "path": "/ukazky-2/index.html",
        "type": "file",
        "md5": "bb3036ea7cfb2b9f8d9fc9d4f7cdec8c"
    }
]